{"cameraMode":{"drawMode":0,"name":"Shaded","section":"Shading Mode"},"sceneLighting":false,"audioPlay":false,"sceneViewState":{"m_AlwaysRefresh":false,"showFog":true,"showSkybox":false,"showFlares":true,"showImageEffects":true,"showParticleSystems":true,"showVisualEffectGraphs":true,"m_FxEnabled":true},"in2DMode":false,"pivot":{"x":-0.9286510944366455,"y":1.6988742351531983,"z":0.22273774445056916},"rotation":{"x":-0.2117113322019577,"y":-0.5189564824104309,"z":0.13444872200489045,"w":-0.8171878457069397},"size":0.7887410521507263,"orthographic":false}